custom_gift_send/__init__.py
custom_gift_send/custom_gift_send.py
custom_gift_send-2.2.0.dist-info/licenses/LICENSE
custom_gift_send-2.2.0.dist-info/METADATA
custom_gift_send-2.2.0.dist-info/WHEEL
custom_gift_send-2.2.0.dist-info/top_level.txt
custom_gift_send-2.2.0.dist-info/RECORD
