Metadata-Version: 2.4
Name: custom-gift-send
Version: 2.2.0
Summary: Улучшенный асинхронный Python-модуль для Telegram Bot API с повышенной безопасностью, аналитикой и новыми функциями.
Home-page: https://github.com/Nsvl/custom-gift-send
Author: Nsvl
Author-email: huff-outer-siding@duck.com
Project-URL: Bug Reports, https://github.com/Nsvl/custom-gift-send/issues
Project-URL: Source, https://github.com/Nsvl/custom-gift-send
Project-URL: Documentation, https://github.com/Nsvl/custom-gift-send/wiki
Project-URL: Telegram Channel, https://t.me/GifterChannel
Keywords: telegram bot api stars gift premium checklist business account circuitbreaker security analytics rate-limiting webhook
Classifier: Development Status :: 5 - Production/Stable
Classifier: Programming Language :: Python :: 3
Classifier: Programming Language :: Python :: 3.8
Classifier: Programming Language :: Python :: 3.9
Classifier: Programming Language :: Python :: 3.10
Classifier: Programming Language :: Python :: 3.11
Classifier: Programming Language :: Python :: 3.12
Classifier: License :: OSI Approved :: MIT License
Classifier: Operating System :: OS Independent
Classifier: Intended Audience :: Developers
Classifier: Topic :: Communications :: Chat
Classifier: Topic :: Software Development :: Libraries :: Python Modules
Classifier: Topic :: Software Development :: Libraries :: Application Frameworks
Classifier: Topic :: Security
Classifier: Topic :: Internet :: WWW/HTTP :: Dynamic Content
Classifier: Framework :: AsyncIO
Requires-Python: >=3.8
License-File: LICENSE
Requires-Dist: aiohttp>=3.8.4
Requires-Dist: pydantic>=2.0.3
Requires-Dist: cachetools>=5.3.1
Requires-Dist: pybreaker>=1.1.0
Requires-Dist: cryptography>=41.0.0
Provides-Extra: dev
Requires-Dist: pytest>=7.0.0; extra == "dev"
Requires-Dist: pytest-asyncio>=0.21.0; extra == "dev"
Requires-Dist: pytest-cov>=4.0.0; extra == "dev"
Requires-Dist: black>=23.0.0; extra == "dev"
Requires-Dist: isort>=5.12.0; extra == "dev"
Requires-Dist: mypy>=1.0.0; extra == "dev"
Provides-Extra: docs
Requires-Dist: sphinx>=6.0.0; extra == "docs"
Requires-Dist: sphinx-rtd-theme>=1.2.0; extra == "docs"
Dynamic: author
Dynamic: author-email
Dynamic: classifier
Dynamic: description
Dynamic: description-content-type
Dynamic: home-page
Dynamic: keywords
Dynamic: license-file
Dynamic: project-url
Dynamic: provides-extra
Dynamic: requires-dist
Dynamic: requires-python
Dynamic: summary
